{
  "$schema": "https://static.modelcontextprotocol.io/schemas/2025-12-11/server.schema.json",
  "name": "io.github.CakeRepository/1password",
  "description": "MCP server for 1Password service accounts",
  "repository": {
    "url": "https://github.com/CakeRepository/1Password-MCP.git",
    "source": "github"
  },
  "version": "1.0.5",
  "packages": [
    {
      "registryType": "npm",
      "identifier": "@takescake/1password-mcp",
      "version": "1.0.5",
      "transport": {
        "type": "stdio"
      },
      "environmentVariables": [
        {
          "name": "OP_SERVICE_ACCOUNT_TOKEN",
          "description": "The Service Account Token from 1Password",
          "isRequired": true,
          "isSecret": true,
          "format": "string"
        }
      ]
    }
  ]
}
